{
    "date": "14.10.2012", 
    "election_name": "Выборы Главы городского округа \"Город Калининград\"", 
    "merge": [
        {
            "merge_id": 39008, 
            "name": "УИК №174", 
            "tvd": "4394009116073"
        }, 
        {
            "merge_id": 39008, 
            "name": "УИК №157", 
            "tvd": "4394009116055"
        }, 
        {
            "merge_id": 39008, 
            "name": "УИК №161", 
            "tvd": "4394009116060"
        }, 
        {
            "merge_id": 39008, 
            "name": "УИК №180", 
            "tvd": "4394009116079"
        }, 
        {
            "merge_id": 39008, 
            "name": "УИК №178", 
            "tvd": "4394009116077"
        }, 
        {
            "merge_id": 39008, 
            "name": "УИК №249", 
            "tvd": "4394009116088"
        }, 
        {
            "merge_id": 39008, 
            "name": "УИК №167", 
            "tvd": "4394009116066"
        }, 
        {
            "merge_id": 39008, 
            "name": "УИК №185", 
            "tvd": "4394009116084"
        }, 
        {
            "merge_id": 39008, 
            "name": "УИК №265", 
            "tvd": "4394009116104"
        }, 
        {
            "merge_id": 39008, 
            "name": "УИК №181", 
            "tvd": "4394009116080"
        }, 
        {
            "merge_id": 39008, 
            "name": "УИК №256", 
            "tvd": "4394009116095"
        }, 
        {
            "merge_id": 39008, 
            "name": "УИК №250", 
            "tvd": "4394009116089"
        }, 
        {
            "merge_id": 39008, 
            "name": "УИК №275", 
            "tvd": "4394009116114"
        }, 
        {
            "merge_id": 39008, 
            "name": "УИК №165", 
            "tvd": "4394009116064"
        }, 
        {
            "merge_id": 39008, 
            "name": "УИК №270", 
            "tvd": "4394009116109"
        }, 
        {
            "merge_id": 39008, 
            "name": "УИК №177", 
            "tvd": "4394009116076"
        }, 
        {
            "merge_id": 39008, 
            "name": "УИК №172", 
            "tvd": "4394009116071"
        }, 
        {
            "merge_id": 39008, 
            "name": "УИК №267", 
            "tvd": "4394009116106"
        }, 
        {
            "merge_id": 39008, 
            "name": "УИК №159", 
            "tvd": "4394009116058"
        }, 
        {
            "merge_id": 39008, 
            "name": "УИК №259", 
            "tvd": "4394009116098"
        }, 
        {
            "merge_id": 39008, 
            "name": "УИК №184", 
            "tvd": "4394009116083"
        }, 
        {
            "merge_id": 39008, 
            "name": "УИК №254", 
            "tvd": "4394009116093"
        }, 
        {
            "merge_id": 39008, 
            "name": "УИК №246", 
            "tvd": "4394009116085"
        }, 
        {
            "merge_id": 39008, 
            "name": "УИК №269", 
            "tvd": "4394009116108"
        }, 
        {
            "merge_id": 39008, 
            "name": "УИК №247", 
            "tvd": "4394009116086"
        }, 
        {
            "merge_id": 39008, 
            "name": "УИК №168", 
            "tvd": "4394009116067"
        }, 
        {
            "merge_id": 39008, 
            "name": "УИК №164", 
            "tvd": "4394009116063"
        }, 
        {
            "merge_id": 39008, 
            "name": "УИК №252", 
            "tvd": "4394009116091"
        }, 
        {
            "merge_id": 39008, 
            "name": "УИК №183", 
            "tvd": "4394009116082"
        }, 
        {
            "merge_id": 39008, 
            "name": "УИК №182", 
            "tvd": "4394009116081"
        }, 
        {
            "merge_id": 39008, 
            "name": "УИК №255", 
            "tvd": "4394009116094"
        }, 
        {
            "merge_id": 39008, 
            "name": "УИК №251", 
            "tvd": "4394009116090"
        }, 
        {
            "merge_id": 39008, 
            "name": "УИК №266", 
            "tvd": "4394009116105"
        }, 
        {
            "merge_id": 39008, 
            "name": "УИК №272", 
            "tvd": "4394009116111"
        }, 
        {
            "merge_id": 39008, 
            "name": "УИК №170", 
            "tvd": "4394009116069"
        }, 
        {
            "merge_id": 39008, 
            "name": "УИК №163", 
            "tvd": "4394009116062"
        }, 
        {
            "merge_id": 39008, 
            "name": "УИК №263", 
            "tvd": "4394009116102"
        }, 
        {
            "merge_id": 39008, 
            "name": "УИК №264", 
            "tvd": "4394009116103"
        }, 
        {
            "merge_id": 39008, 
            "name": "УИК №158", 
            "tvd": "4394009116057"
        }, 
        {
            "merge_id": 39008, 
            "name": "УИК №173", 
            "tvd": "4394009116072"
        }, 
        {
            "merge_id": 39008, 
            "name": "УИК №258", 
            "tvd": "4394009116097"
        }, 
        {
            "merge_id": 39008, 
            "name": "УИК №162", 
            "tvd": "4394009116061"
        }, 
        {
            "merge_id": 39008, 
            "name": "УИК №171", 
            "tvd": "4394009116070"
        }, 
        {
            "merge_id": 39008, 
            "name": "УИК №273", 
            "tvd": "4394009116112"
        }, 
        {
            "merge_id": 39008, 
            "name": "УИК №260", 
            "tvd": "4394009116099"
        }, 
        {
            "merge_id": 39008, 
            "name": "УИК №160", 
            "tvd": "4394009116059"
        }, 
        {
            "merge_id": 39008, 
            "name": "УИК №268", 
            "tvd": "4394009116107"
        }, 
        {
            "merge_id": 39008, 
            "name": "УИК №253", 
            "tvd": "4394009116092"
        }, 
        {
            "merge_id": 39008, 
            "name": "УИК №274", 
            "tvd": "4394009116113"
        }, 
        {
            "merge_id": 39008, 
            "name": "УИК №271", 
            "tvd": "4394009116110"
        }, 
        {
            "merge_id": 39008, 
            "name": "УИК №261", 
            "tvd": "4394009116100"
        }, 
        {
            "merge_id": 39008, 
            "name": "УИК №262", 
            "tvd": "4394009116101"
        }, 
        {
            "merge_id": 39008, 
            "name": "УИК №257", 
            "tvd": "4394009116096"
        }, 
        {
            "merge_id": 39008, 
            "name": "УИК №175", 
            "tvd": "4394009116074"
        }, 
        {
            "merge_id": 39008, 
            "name": "УИК №169", 
            "tvd": "4394009116068"
        }, 
        {
            "merge_id": 39008, 
            "name": "УИК №166", 
            "tvd": "4394009116065"
        }, 
        {
            "merge_id": 39008, 
            "name": "УИК №248", 
            "tvd": "4394009116087"
        }, 
        {
            "merge_id": 39008, 
            "name": "УИК №179", 
            "tvd": "4394009116078"
        }, 
        {
            "merge_id": 39008, 
            "name": "УИК №176", 
            "tvd": "4394009116075"
        }, 
        {
            "merge_id": 39009, 
            "name": "УИК №303", 
            "tvd": "4394011107730"
        }, 
        {
            "merge_id": 39009, 
            "name": "УИК №320", 
            "tvd": "4394011107747"
        }, 
        {
            "merge_id": 39009, 
            "name": "УИК №276", 
            "tvd": "4394011107705"
        }, 
        {
            "merge_id": 39009, 
            "name": "УИК №300", 
            "tvd": "4394011107727"
        }, 
        {
            "merge_id": 39009, 
            "name": "УИК №298", 
            "tvd": "4394011107725"
        }, 
        {
            "merge_id": 39009, 
            "name": "УИК №322", 
            "tvd": "4394011107749"
        }, 
        {
            "merge_id": 39009, 
            "name": "УИК №304", 
            "tvd": "4394011107731"
        }, 
        {
            "merge_id": 39009, 
            "name": "УИК №301", 
            "tvd": "4394011107728"
        }, 
        {
            "merge_id": 39009, 
            "name": "УИК №306", 
            "tvd": "4394011107733"
        }, 
        {
            "merge_id": 39009, 
            "name": "УИК №282", 
            "tvd": "4394011107711"
        }, 
        {
            "merge_id": 39009, 
            "name": "УИК №295", 
            "tvd": "4394011107722"
        }, 
        {
            "merge_id": 39009, 
            "name": "УИК №283", 
            "tvd": "4394011107712"
        }, 
        {
            "merge_id": 39009, 
            "name": "УИК №308", 
            "tvd": "4394011107735"
        }, 
        {
            "merge_id": 39009, 
            "name": "УИК №314", 
            "tvd": "4394011107741"
        }, 
        {
            "merge_id": 39009, 
            "name": "УИК №284", 
            "tvd": "4394011107713"
        }, 
        {
            "merge_id": 39009, 
            "name": "УИК №296", 
            "tvd": "4394011107723"
        }, 
        {
            "merge_id": 39009, 
            "name": "УИК №302", 
            "tvd": "4394011107729"
        }, 
        {
            "merge_id": 39009, 
            "name": "УИК №309", 
            "tvd": "4394011107736"
        }, 
        {
            "merge_id": 39009, 
            "name": "УИК №293", 
            "tvd": "4394011107852"
        }, 
        {
            "merge_id": 39009, 
            "name": "УИК №281", 
            "tvd": "4394011107710"
        }, 
        {
            "merge_id": 39009, 
            "name": "УИК №318", 
            "tvd": "4394011107745"
        }, 
        {
            "merge_id": 39009, 
            "name": "УИК №317", 
            "tvd": "4394011107744"
        }, 
        {
            "merge_id": 39009, 
            "name": "УИК №290", 
            "tvd": "4394011107719"
        }, 
        {
            "merge_id": 39009, 
            "name": "УИК №287", 
            "tvd": "4394011107716"
        }, 
        {
            "merge_id": 39009, 
            "name": "УИК №277", 
            "tvd": "4394011107706"
        }, 
        {
            "merge_id": 39009, 
            "name": "УИК №319", 
            "tvd": "4394011107746"
        }, 
        {
            "merge_id": 39009, 
            "name": "УИК №321", 
            "tvd": "4394011107748"
        }, 
        {
            "merge_id": 39009, 
            "name": "УИК №305", 
            "tvd": "4394011107732"
        }, 
        {
            "merge_id": 39009, 
            "name": "УИК №285", 
            "tvd": "4394011107714"
        }, 
        {
            "merge_id": 39009, 
            "name": "УИК №313", 
            "tvd": "4394011107740"
        }, 
        {
            "merge_id": 39009, 
            "name": "УИК №297", 
            "tvd": "4394011107724"
        }, 
        {
            "merge_id": 39009, 
            "name": "УИК №307", 
            "tvd": "4394011107734"
        }, 
        {
            "merge_id": 39009, 
            "name": "УИК №279", 
            "tvd": "4394011107708"
        }, 
        {
            "merge_id": 39009, 
            "name": "УИК №315", 
            "tvd": "4394011107742"
        }, 
        {
            "merge_id": 39009, 
            "name": "УИК №292", 
            "tvd": "4394011107721"
        }, 
        {
            "merge_id": 39009, 
            "name": "УИК №311", 
            "tvd": "4394011107738"
        }, 
        {
            "merge_id": 39009, 
            "name": "УИК №316", 
            "tvd": "4394011107743"
        }, 
        {
            "merge_id": 39009, 
            "name": "УИК №288", 
            "tvd": "4394011107717"
        }, 
        {
            "merge_id": 39009, 
            "name": "УИК №289", 
            "tvd": "4394011107718"
        }, 
        {
            "merge_id": 39009, 
            "name": "УИК №312", 
            "tvd": "4394011107739"
        }, 
        {
            "merge_id": 39009, 
            "name": "УИК №299", 
            "tvd": "4394011107726"
        }, 
        {
            "merge_id": 39009, 
            "name": "УИК №310", 
            "tvd": "4394011107737"
        }, 
        {
            "merge_id": 39009, 
            "name": "УИК №278", 
            "tvd": "4394011107707"
        }, 
        {
            "merge_id": 39009, 
            "name": "УИК №286", 
            "tvd": "4394011107715"
        }, 
        {
            "merge_id": 39009, 
            "name": "УИК №291", 
            "tvd": "4394011107720"
        }, 
        {
            "merge_id": 39009, 
            "name": "УИК №280", 
            "tvd": "4394011107709"
        }, 
        {
            "merge_id": 39007, 
            "name": "УИК №234", 
            "tvd": "4394008115696"
        }, 
        {
            "merge_id": 39007, 
            "name": "УИК №189", 
            "tvd": "4394008115653"
        }, 
        {
            "merge_id": 39007, 
            "name": "УИК №230", 
            "tvd": "4394008115692"
        }, 
        {
            "merge_id": 39007, 
            "name": "УИК №201", 
            "tvd": "4394008115665"
        }, 
        {
            "merge_id": 39007, 
            "name": "УИК №217", 
            "tvd": "4394008115679"
        }, 
        {
            "merge_id": 39007, 
            "name": "УИК №221", 
            "tvd": "4394008115683"
        }, 
        {
            "merge_id": 39007, 
            "name": "УИК №244", 
            "tvd": "4394008115706"
        }, 
        {
            "merge_id": 39007, 
            "name": "УИК №223", 
            "tvd": "4394008115685"
        }, 
        {
            "merge_id": 39007, 
            "name": "УИК №211", 
            "tvd": "4394008115675"
        }, 
        {
            "merge_id": 39007, 
            "name": "УИК №195", 
            "tvd": "4394008115659"
        }, 
        {
            "merge_id": 39007, 
            "name": "УИК №207", 
            "tvd": "4394008115671"
        }, 
        {
            "merge_id": 39007, 
            "name": "УИК №208", 
            "tvd": "4394008115672"
        }, 
        {
            "merge_id": 39007, 
            "name": "УИК №213", 
            "tvd": "4394008115676"
        }, 
        {
            "merge_id": 39007, 
            "name": "УИК №209", 
            "tvd": "4394008115673"
        }, 
        {
            "merge_id": 39007, 
            "name": "УИК №212", 
            "tvd": "4394008115708"
        }, 
        {
            "merge_id": 39007, 
            "name": "УИК №222", 
            "tvd": "4394008115684"
        }, 
        {
            "merge_id": 39007, 
            "name": "УИК №232", 
            "tvd": "4394008115694"
        }, 
        {
            "merge_id": 39007, 
            "name": "УИК №216", 
            "tvd": "4394008115678"
        }, 
        {
            "merge_id": 39007, 
            "name": "УИК №198", 
            "tvd": "4394008115662"
        }, 
        {
            "merge_id": 39007, 
            "name": "УИК №197", 
            "tvd": "4394008115661"
        }, 
        {
            "merge_id": 39007, 
            "name": "УИК №206", 
            "tvd": "4394008115670"
        }, 
        {
            "merge_id": 39007, 
            "name": "УИК №228", 
            "tvd": "4394008115690"
        }, 
        {
            "merge_id": 39007, 
            "name": "УИК №241", 
            "tvd": "4394008115703"
        }, 
        {
            "merge_id": 39007, 
            "name": "УИК №202", 
            "tvd": "4394008115666"
        }, 
        {
            "merge_id": 39007, 
            "name": "УИК №186", 
            "tvd": "4394008115650"
        }, 
        {
            "merge_id": 39007, 
            "name": "УИК №188", 
            "tvd": "4394008115652"
        }, 
        {
            "merge_id": 39007, 
            "name": "УИК №236", 
            "tvd": "4394008115698"
        }, 
        {
            "merge_id": 39007, 
            "name": "УИК №225", 
            "tvd": "4394008115687"
        }, 
        {
            "merge_id": 39007, 
            "name": "УИК №220", 
            "tvd": "4394008115682"
        }, 
        {
            "merge_id": 39007, 
            "name": "УИК №243", 
            "tvd": "4394008115705"
        }, 
        {
            "merge_id": 39007, 
            "name": "УИК №204", 
            "tvd": "4394008115668"
        }, 
        {
            "merge_id": 39007, 
            "name": "УИК №205", 
            "tvd": "4394008115669"
        }, 
        {
            "merge_id": 39007, 
            "name": "УИК №203", 
            "tvd": "4394008115667"
        }, 
        {
            "merge_id": 39007, 
            "name": "УИК №227", 
            "tvd": "4394008115689"
        }, 
        {
            "merge_id": 39007, 
            "name": "УИК №194", 
            "tvd": "4394008115658"
        }, 
        {
            "merge_id": 39007, 
            "name": "УИК №214", 
            "tvd": "4394008115677"
        }, 
        {
            "merge_id": 39007, 
            "name": "УИК №193", 
            "tvd": "4394008115657"
        }, 
        {
            "merge_id": 39007, 
            "name": "УИК №226", 
            "tvd": "4394008115688"
        }, 
        {
            "merge_id": 39007, 
            "name": "УИК №235", 
            "tvd": "4394008115697"
        }, 
        {
            "merge_id": 39007, 
            "name": "УИК №242", 
            "tvd": "4394008115704"
        }, 
        {
            "merge_id": 39007, 
            "name": "УИК №199", 
            "tvd": "4394008115663"
        }, 
        {
            "merge_id": 39007, 
            "name": "УИК №192", 
            "tvd": "4394008115656"
        }, 
        {
            "merge_id": 39007, 
            "name": "УИК №233", 
            "tvd": "4394008115695"
        }, 
        {
            "merge_id": 39007, 
            "name": "УИК №231", 
            "tvd": "4394008115693"
        }, 
        {
            "merge_id": 39007, 
            "name": "УИК №190", 
            "tvd": "4394008115654"
        }, 
        {
            "merge_id": 39007, 
            "name": "УИК №229", 
            "tvd": "4394008115691"
        }, 
        {
            "merge_id": 39007, 
            "name": "УИК №219", 
            "tvd": "4394008115681"
        }, 
        {
            "merge_id": 39007, 
            "name": "УИК №237", 
            "tvd": "4394008115699"
        }, 
        {
            "merge_id": 39007, 
            "name": "УИК №191", 
            "tvd": "4394008115655"
        }, 
        {
            "merge_id": 39007, 
            "name": "УИК №224", 
            "tvd": "4394008115686"
        }, 
        {
            "merge_id": 39007, 
            "name": "УИК №238", 
            "tvd": "4394008115700"
        }, 
        {
            "merge_id": 39007, 
            "name": "УИК №240", 
            "tvd": "4394008115702"
        }, 
        {
            "merge_id": 39007, 
            "name": "УИК №218", 
            "tvd": "4394008115680"
        }, 
        {
            "merge_id": 39007, 
            "name": "УИК №187", 
            "tvd": "4394008115651"
        }, 
        {
            "merge_id": 39007, 
            "name": "УИК №210", 
            "tvd": "4394008115674"
        }, 
        {
            "merge_id": 39007, 
            "name": "УИК №239", 
            "tvd": "4394008115701"
        }, 
        {
            "merge_id": 39007, 
            "name": "УИК №200", 
            "tvd": "4394008115664"
        }, 
        {
            "merge_id": 39007, 
            "name": "УИК №196", 
            "tvd": "4394008115660"
        }, 
        {
            "merge_id": 39007, 
            "name": "УИК №245", 
            "tvd": "4394008115707"
        }
    ], 
    "prver": "0", 
    "region_id": 39, 
    "vrn": "2392000276721"
}